<?xml version="1.0" encoding="UTF-8"?>
<alpino_ds version="1.6">
  <parser build="Alpino-x86_64-linux-glibc2.5-git233-sicstus" date="2021-02-02T16:13" cats="1" skips="0" />
  <node begin="0" cat="top" end="7" id="0" rel="top">
    <node begin="0" cat="smain" end="7" id="1" rel="--">
      <node begin="0" cat="np" end="2" id="2" rel="su">
        <node begin="0" buiging="met-e" end="1" frame="determiner(pl_num,nwh,nmod,pro,yparg)" his="normal" his_1="decap" his_1_1="normal" id="3" infl="pl_num" lcat="detp" lemma="sommig" naamval="stan" npagr="rest" pdtype="det" pos="det" positie="prenom" postag="VNW(onbep,det,stan,prenom,met-e,rest)" pt="vnw" rel="det" root="sommig" sense="sommig" vwtype="onbep" wh="nwh" word="Sommige"/>
        <node begin="1" end="2" frame="noun(het,count,pl)" gen="het" getal="mv" graad="basis" his="normal" his_1="normal" id="4" lcat="np" lemma="tiener_meisje" ntype="soort" num="pl" pos="noun" postag="N(soort,mv,basis)" pt="n" rel="hd" rnum="pl" root="tiener_meisje" sense="tiener_meisje" word="tienermeisjes"/>
      </node>
      <node begin="2" end="3" frame="verb(hebben,pl,part_intransitive(stil))" his="normal" his_1="normal" id="5" infl="pl" lcat="smain" lemma="stil_staan" pos="verb" postag="WW(pv,tgw,mv)" pt="ww" pvagr="mv" pvtijd="tgw" rel="hd" root="sta_stil" sc="part_intransitive(stil)" sense="sta_stil" stype="declarative" tense="present" word="staan" wvorm="pv"/>
      <node begin="3" buiging="zonder" end="4" frame="particle(stil)" graad="basis" his="normal" his_1="normal" id="6" lcat="part" lemma="stil" pos="part" positie="vrij" postag="ADJ(vrij,basis,zonder)" pt="adj" rel="svp" root="stil" sense="stil" word="stil"/>
      <node begin="4" cat="pp" end="7" id="7" rel="mod">
        <node begin="4" end="5" frame="preposition(voor,[aan,door,uit,[in,de,plaats]])" his="normal" his_1="normal" id="8" lcat="pp" lemma="voor" pos="prep" postag="VZ(init)" pt="vz" rel="hd" root="voor" sense="voor" vztype="init" word="voor"/>
        <node begin="5" cat="np" end="7" id="9" rel="obj1">
          <node begin="5" end="6" frame="determiner(de)" his="normal" his_1="normal" id="10" infl="de" lcat="detp" lemma="de" lwtype="bep" naamval="stan" npagr="rest" pos="det" postag="LID(bep,stan,rest)" pt="lid" rel="det" root="de" sense="de" word="de"/>
          <node begin="6" end="7" frame="noun(de,count,sg)" gen="de" genus="zijd" getal="ev" graad="basis" his="normal" his_1="normal" id="11" lcat="np" lemma="camera" naamval="stan" ntype="soort" num="sg" pos="noun" postag="N(soort,ev,basis,zijd,stan)" pt="n" rel="hd" rnum="sg" root="camera" sense="camera" word="camera"/>
        </node>
      </node>
    </node>
  </node>
  <sentence sentid="1888">Sommige tienermeisjes staan stil voor de camera</sentence>
  <comments>
    <comment>Q#1888|Sommige tienermeisjes staan stil voor de camera|1|1|-3.117311966400001</comment>
  </comments>
</alpino_ds>
