<?xml version="1.0" encoding="UTF-8"?>
<alpino_ds version="1.6">
  <parser build="Alpino-x86_64-linux-glibc2.5-git233-sicstus" date="2021-02-02T16:17" cats="1" skips="0" />
  <node begin="0" cat="top" end="12" id="0" rel="top">
    <node begin="0" cat="smain" end="12" id="1" rel="--">
      <node begin="0" cat="np" end="2" id="2" index="1" rel="su">
        <node begin="0" end="1" frame="determiner(een)" his="normal" his_1="decap" his_1_1="normal" id="3" infl="een" lcat="detp" lemma="een" lwtype="onbep" naamval="stan" npagr="agr" pos="det" postag="LID(onbep,stan,agr)" pt="lid" rel="det" root="een" sense="een" word="Een"/>
        <node begin="1" end="2" frame="noun(de,count,bare_meas)" gen="de" genus="zijd" getal="ev" graad="basis" his="normal" his_1="normal" id="4" lcat="np" lemma="man" naamval="stan" ntype="soort" num="bare_meas" pos="noun" postag="N(soort,ev,basis,zijd,stan)" pt="n" rel="hd" rnum="sg" root="man" sense="man" word="man"/>
      </node>
      <node begin="2" end="3" frame="verb(unacc,sg_heeft,aan_het)" his="normal" his_1="normal" id="5" infl="sg_heeft" lcat="smain" lemma="zijn" pos="verb" postag="WW(pv,tgw,ev)" pt="ww" pvagr="ev" pvtijd="tgw" rel="hd" root="ben" sc="aan_het" sense="ben-aan_het" stype="declarative" tense="present" word="is" wvorm="pv"/>
      <node begin="0" cat="ahi" end="12" id="6" rel="vc">
        <node begin="6" cat="mwu" end="8" his="normal" his_1="normal" id="7" mwu_root="aan het" mwu_sense="aan het" rel="cmp">
          <node begin="6" end="7" frame="complementizer(aan_het)" id="8" lcat="ahi" lemma="aan" pos="comp" postag="VZ(init)" pt="vz" rel="mwp" root="aan" sc="aan_het" sense="aan" vztype="init" word="aan"/>
          <node begin="7" end="8" frame="complementizer(aan_het)" id="9" lcat="ahi" lemma="het" lwtype="bep" naamval="stan" npagr="evon" pos="comp" postag="LID(bep,stan,evon)" pt="lid" rel="mwp" root="het" sc="aan_het" sense="het" word="het"/>
        </node>
        <node begin="0" cat="inf" end="12" id="10" rel="body">
          <node begin="0" end="2" id="11" index="1" rel="su"/>
          <node aform="base" begin="3" buiging="zonder" end="4" frame="adjective(no_e(adv))" graad="basis" his="normal" his_1="normal" id="12" infl="no_e" lcat="ap" lemma="vlug" pos="adj" positie="vrij" postag="ADJ(vrij,basis,zonder)" pt="adj" rel="mod" root="vlug" sense="vlug" vform="adj" word="vlug"/>
          <node begin="4" cat="np" end="6" id="13" rel="obj1">
            <node begin="4" end="5" frame="determiner(wat,nwh,mod,pro,nparg,ntopicpro)" getal="ev" his="normal" his_1="normal" id="14" infl="wat" lcat="detp" lemma="wat" naamval="stan" pdtype="pron" persoon="3o" pos="det" postag="VNW(onbep,pron,stan,vol,3o,ev)" pt="vnw" rel="det" root="wat" sense="wat" status="vol" vwtype="onbep" wh="nwh" word="wat"/>
            <node begin="5" end="6" frame="noun(de,count,pl)" gen="de" getal="mv" graad="basis" his="normal" his_1="normal" id="15" lcat="np" lemma="champignon" ntype="soort" num="pl" pos="noun" postag="N(soort,mv,basis)" pt="n" rel="hd" rnum="pl" root="champignon" sense="champignon" word="champignons"/>
          </node>
          <node begin="8" buiging="zonder" end="9" frame="verb(hebben,inf,transitive)" his="normal" his_1="normal" id="16" infl="inf" lcat="inf" lemma="hakken" pos="verb" positie="vrij" postag="WW(inf,vrij,zonder)" pt="ww" rel="hd" root="hak" sc="transitive" sense="hak" word="hakken" wvorm="inf"/>
          <node begin="9" cat="pp" end="12" id="17" rel="mod">
            <node begin="9" end="10" frame="preposition(met,[mee,[en,al]])" his="normal" his_1="normal" id="18" lcat="pp" lemma="met" pos="prep" postag="VZ(init)" pt="vz" rel="hd" root="met" sense="met" vztype="init" word="met"/>
            <node begin="10" cat="np" end="12" id="19" rel="obj1">
              <node begin="10" end="11" frame="determiner(een)" his="normal" his_1="normal" id="20" infl="een" lcat="detp" lemma="een" lwtype="onbep" naamval="stan" npagr="agr" pos="det" postag="LID(onbep,stan,agr)" pt="lid" rel="det" root="een" sense="een" word="een"/>
              <node begin="11" end="12" frame="noun(het,count,sg)" gen="het" genus="onz" getal="ev" graad="basis" his="normal" his_1="normal" id="21" lcat="np" lemma="mes" naamval="stan" ntype="soort" num="sg" pos="noun" postag="N(soort,ev,basis,onz,stan)" pt="n" rel="hd" rnum="sg" root="mes" sense="mes" word="mes"/>
            </node>
          </node>
        </node>
      </node>
    </node>
  </node>
  <sentence sentid="2633">Een man is vlug wat champignons aan het hakken met een mes</sentence>
  <comments>
    <comment>Q#2633|Een man is vlug wat champignons aan het hakken met een mes|1|1|-5.787538948100001</comment>
  </comments>
</alpino_ds>
