<?xml version="1.0" encoding="UTF-8"?>
<alpino_ds version="1.6">
  <parser build="Alpino-x86_64-linux-glibc2.5-git233-sicstus" date="2021-02-02T16:02" cats="1" skips="0" />
  <node begin="0" cat="top" end="8" id="0" rel="top">
    <node begin="0" cat="smain" end="8" id="1" rel="--">
      <node begin="0" cat="np" end="2" id="2" rel="su">
        <node begin="0" end="1" frame="determiner(een)" his="normal" his_1="decap" his_1_1="normal" id="3" infl="een" lcat="detp" lemma="een" lwtype="onbep" naamval="stan" npagr="agr" pos="det" postag="LID(onbep,stan,agr)" pt="lid" rel="det" root="een" sense="een" word="Een"/>
        <node begin="1" end="2" frame="noun(het,count,sg)" gen="het" genus="onz" getal="ev" graad="basis" his="normal" his_1="normal" id="4" lcat="np" lemma="tiener_meisje" naamval="stan" ntype="soort" num="sg" pos="noun" postag="N(soort,ev,basis,onz,stan)" pt="n" rel="hd" rnum="sg" root="tiener_meisje" sense="tiener_meisje" word="tienermeisje"/>
      </node>
      <node begin="2" end="3" frame="verb(hebben,sg3,part_transitive(op))" his="normal" his_1="normal" id="5" infl="sg3" lcat="smain" lemma="op_slaan" pos="verb" postag="WW(pv,tgw,met-t)" pt="ww" pvagr="met-t" pvtijd="tgw" rel="hd" root="sla_op" sc="part_transitive(op)" sense="sla_op" stype="declarative" tense="present" word="slaat" wvorm="pv"/>
      <node begin="4" end="5" frame="particle(op)" his="normal" his_1="normal" id="6" lcat="part" lemma="op" pos="part" postag="VZ(fin)" pt="vz" rel="svp" root="op" sense="op" vztype="fin" word="op"/>
      <node begin="3" cat="np" end="8" id="7" rel="obj1">
        <node begin="3" end="4" frame="noun(de,count,pl)" gen="de" getal="mv" graad="basis" his="normal" his_1="normal" id="8" lcat="np" lemma="kraal" ntype="soort" num="pl" pos="noun" postag="N(soort,mv,basis)" pt="n" rel="hd" rnum="pl" root="kraal" sense="kraal" word="kralen"/>
        <node begin="5" cat="rel" end="8" id="9" rel="mod">
          <node begin="5" case="no_obl" end="6" frame="rel_pronoun(de,no_obl)" gen="de" getal="getal" his="normal" his_1="normal" id="10" index="1" lcat="np" lemma="die" naamval="stan" pdtype="pron" persoon="persoon" pos="pron" postag="VNW(betr,pron,stan,vol,persoon,getal)" pt="vnw" rel="rhd" rnum="pl" root="die" sense="die" status="vol" vwtype="betr" wh="rel" word="die"/>
          <node begin="5" cat="ssub" end="8" id="11" rel="body">
            <node begin="5" end="6" id="12" index="1" rel="su"/>
            <node aform="base" begin="6" buiging="zonder" end="7" frame="adjective(no_e(adv))" graad="basis" his="normal" his_1="normal" id="13" infl="no_e" lcat="ap" lemma="rood" pos="adj" positie="vrij" postag="ADJ(vrij,basis,zonder)" pt="adj" rel="predc" root="rood" sense="rood" vform="adj" word="rood"/>
            <node begin="7" end="8" frame="verb(unacc,pl,copula)" his="normal" his_1="normal" id="14" infl="pl" lcat="ssub" lemma="zijn" pos="verb" postag="WW(pv,tgw,mv)" pt="ww" pvagr="mv" pvtijd="tgw" rel="hd" root="ben" sc="copula" sense="ben" tense="present" word="zijn" wvorm="pv"/>
          </node>
        </node>
      </node>
    </node>
  </node>
  <sentence sentid="388">Een tienermeisje slaat kralen op die rood zijn</sentence>
  <comments>
    <comment>Q#388|Een tienermeisje slaat kralen op die rood zijn|1|1|-2.300047338000002</comment>
  </comments>
</alpino_ds>
