<?xml version="1.0" encoding="UTF-8"?>
<alpino_ds version="1.6">
  <parser build="Alpino-x86_64-linux-glibc2.5-git233-sicstus" date="2021-02-02T16:40" cats="1" skips="0" />
  <node begin="0" cat="top" end="15" id="0" rel="top">
    <node begin="3" end="4" frame="punct(komma)" his="normal" his_1="normal" id="1" lcat="punct" lemma="," pos="punct" postag="LET()" pt="let" rel="--" root="," sense="," special="komma" word=","/>
    <node begin="9" end="10" frame="punct(komma)" his="normal" his_1="normal" id="2" lcat="punct" lemma="," pos="punct" postag="LET()" pt="let" rel="--" root="," sense="," special="komma" word=","/>
    <node begin="0" cat="smain" end="15" id="3" rel="--">
      <node begin="0" cat="conj" end="9" id="4" rel="su">
        <node begin="0" cat="np" end="3" id="5" rel="cnj">
          <node begin="0" end="1" frame="number(hoofd(pl_num))" his="normal" his_1="decap" his_1_1="number_expression" id="6" infl="pl_num" lcat="detp" lemma="twee" naamval="stan" numtype="hoofd" pos="num" positie="prenom" postag="TW(hoofd,prenom,stan)" pt="tw" rel="det" root="twee" sense="twee" special="hoofd" word="Twee"/>
          <node aform="base" begin="1" buiging="met-e" end="2" frame="adjective(e)" graad="basis" his="normal" his_1="normal" id="7" infl="e" lcat="ap" lemma="groot" naamval="stan" pos="adj" positie="prenom" postag="ADJ(prenom,basis,met-e,stan)" pt="adj" rel="mod" root="groot" sense="groot" vform="adj" word="grote"/>
          <node begin="2" end="3" frame="noun(de,count,pl)" gen="de" getal="mv" graad="basis" his="normal" his_1="normal" id="8" lcat="np" lemma="hond" ntype="soort" num="pl" pos="noun" postag="N(soort,mv,basis)" pt="n" rel="hd" rnum="pl" root="hond" sense="hond" word="honden"/>
        </node>
        <node begin="4" cat="np" end="6" id="9" rel="cnj">
          <node begin="4" end="5" frame="determiner(een)" his="normal" his_1="normal" id="10" infl="een" lcat="detp" lemma="een" lwtype="onbep" naamval="stan" npagr="agr" pos="det" postag="LID(onbep,stan,agr)" pt="lid" rel="det" root="een" sense="een" word="een"/>
          <node begin="5" end="6" frame="noun(both,both,both)" gen="both" genus="zijd" getal="ev" graad="basis" his="noun" id="11" lcat="np" lemma="lichtgekleurde" naamval="stan" ntype="soort" num="both" pos="noun" postag="N(soort,ev,basis,zijd,stan)" pt="n" rel="hd" rnum="sg" root="lichtgekleurde" sense="lichtgekleurde" word="lichtgekleurde"/>
        </node>
        <node begin="6" conjtype="neven" end="7" frame="conj(en)" his="normal" his_1="normal" id="12" lcat="vg" lemma="en" pos="vg" postag="VG(neven)" pt="vg" rel="crd" root="en" sense="en" word="en"/>
        <node begin="7" cat="np" end="9" id="13" rel="cnj">
          <node begin="7" end="8" frame="determiner(een)" his="normal" his_1="normal" id="14" infl="een" lcat="detp" lemma="een" lwtype="onbep" naamval="stan" npagr="agr" pos="det" postag="LID(onbep,stan,agr)" pt="lid" rel="det" root="een" sense="een" word="een"/>
          <node aform="base" begin="8" buiging="met-e" end="9" frame="adjective(e)" getal-n="zonder-n" graad="basis" his="normal" his_1="normal" id="15" infl="e" lcat="np" lemma="donker" naamval="stan" pos="adj" positie="nom" postag="ADJ(nom,basis,met-e,zonder-n,stan)" pt="adj" rel="hd" rnum="sg" root="donker" sense="donker" vform="adj" word="donkere"/>
        </node>
      </node>
      <node begin="10" end="11" frame="verb(hebben,pl,intransitive)" his="normal" his_1="normal" id="16" infl="pl" lcat="smain" lemma="slapen" pos="verb" postag="WW(pv,tgw,mv)" pt="ww" pvagr="mv" pvtijd="tgw" rel="hd" root="slaap" sc="intransitive" sense="slaap" stype="declarative" tense="present" word="slapen" wvorm="pv"/>
      <node begin="11" cat="pp" end="15" id="17" rel="mod">
        <node begin="11" end="12" frame="preposition(op,[af,na])" his="normal" his_1="normal" id="18" lcat="pp" lemma="op" pos="prep" postag="VZ(init)" pt="vz" rel="hd" root="op" sense="op" vztype="init" word="op"/>
        <node begin="12" cat="np" end="15" id="19" rel="obj1">
          <node begin="12" end="13" frame="determiner(een)" his="normal" his_1="normal" id="20" infl="een" lcat="detp" lemma="een" lwtype="onbep" naamval="stan" npagr="agr" pos="det" postag="LID(onbep,stan,agr)" pt="lid" rel="det" root="een" sense="een" word="een"/>
          <node aform="base" begin="13" buiging="zonder" end="14" frame="adjective(no_e(adv))" graad="basis" his="normal" his_1="normal" id="21" infl="no_e" lcat="ap" lemma="besneeuwd" pos="adj" positie="prenom" postag="ADJ(prenom,basis,zonder)" pt="adj" rel="mod" root="besneeuwd" sense="besneeuwd" vform="adj" word="besneeuwd"/>
          <node begin="14" end="15" frame="noun(het,count,sg)" gen="het" genus="onz" getal="ev" graad="basis" his="normal" his_1="normal" id="22" lcat="np" lemma="terrein" naamval="stan" ntype="soort" num="sg" pos="noun" postag="N(soort,ev,basis,onz,stan)" pt="n" rel="hd" rnum="sg" root="terrein" sense="terrein" word="terrein"/>
        </node>
      </node>
    </node>
  </node>
  <sentence sentid="5147">Twee grote honden , een lichtgekleurde en een donkere , slapen op een besneeuwd terrein</sentence>
  <comments>
    <comment>Q#5147|Twee grote honden , een lichtgekleurde en een donkere , slapen op een besneeuwd terrein|1|1|-8.530950543499994</comment>
  </comments>
</alpino_ds>
